pexpect_executor/__init__.py
pexpect_executor/__main__.py
pexpect_executor/cli/__init__.py
pexpect_executor/cli/entrypoint.py
pexpect_executor/cli/main.py
pexpect_executor/engines/__init__.py
pexpect_executor/engines/base.py
pexpect_executor/engines/engine.py
pexpect_executor/engines/pexpect.py
pexpect_executor/engines/pexpect_popen.py
pexpect_executor/engines/wexpect.py
pexpect_executor/features/__init__.py
pexpect_executor/features/actions.py
pexpect_executor/lib/__init__.py
pexpect_executor/lib/executor.py
pexpect_executor/package/__init__.py
pexpect_executor/package/bundle.py
pexpect_executor/package/settings.py
pexpect_executor/package/updates.py
pexpect_executor/package/version.py
pexpect_executor/prints/__init__.py
pexpect_executor/prints/boxes.py
pexpect_executor/prints/colors.py
pexpect_executor/system/__init__.py
pexpect_executor/system/platform.py
pexpect_executor/types/__init__.py
pexpect_executor/types/commands.py
pexpect_executor/types/strings.py
pexpect_executor-4.3.1.dist-info/licenses/LICENSE
pexpect_executor-4.3.1.dist-info/METADATA
pexpect_executor-4.3.1.dist-info/WHEEL
pexpect_executor-4.3.1.dist-info/entry_points.txt
pexpect_executor-4.3.1.dist-info/top_level.txt
pexpect_executor-4.3.1.dist-info/RECORD
